LICENSE
MANIFEST.in
requirements.txt
setup.cfg
setup.py
test-requirements.txt
graphite_beacon/__init__.py
graphite_beacon/_compat.py
graphite_beacon/alerts.py
graphite_beacon/app.py
graphite_beacon/core.py
graphite_beacon/graphite.py
graphite_beacon/template.py
graphite_beacon/units.py
graphite_beacon/utils.py
graphite_beacon/handlers/__init__.py
graphite_beacon/handlers/cli.py
graphite_beacon/handlers/hipchat.py
graphite_beacon/handlers/http.py
graphite_beacon/handlers/log.py
graphite_beacon/handlers/opsgenie.py
graphite_beacon/handlers/pagerduty.py
graphite_beacon/handlers/slack.py
graphite_beacon/handlers/smtp.py
graphite_beacon/handlers/telegram.py
graphite_beacon/handlers/victorops.py
graphite_beacon/templates/base.html
graphite_beacon/templates/common/message.html
graphite_beacon/templates/common/message.txt
graphite_beacon/templates/common/short.txt
graphite_beacon/templates/graphite/message.html
graphite_beacon/templates/graphite/message.txt
graphite_beacon/templates/graphite/short.txt
graphite_beacon/templates/graphite/slack.txt
graphite_beacon/templates/url/message.html
graphite_beacon/templates/url/message.txt
graphite_beacon/templates/url/short.txt
graphite_beacon_opsgenie_v2.egg-info/PKG-INFO
graphite_beacon_opsgenie_v2.egg-info/SOURCES.txt
graphite_beacon_opsgenie_v2.egg-info/dependency_links.txt
graphite_beacon_opsgenie_v2.egg-info/entry_points.txt
graphite_beacon_opsgenie_v2.egg-info/requires.txt
graphite_beacon_opsgenie_v2.egg-info/top_level.txt