Metadata-Version: 1.1
Name: graphite-beacon-opsgenie-v2
Version: 0.27.3
Summary: Simple alerting system for Graphite metrics.
